CHANGES.txt
LICENSE.txt
MANIFEST.in
README.rst
setup.py
doc/Makefile
doc/conf.py
doc/ewmh.rst
doc/index.rst
ewmh/__init__.py
ewmh/ewmh.py
ewmh.egg-info/PKG-INFO
ewmh.egg-info/SOURCES.txt
ewmh.egg-info/dependency_links.txt
ewmh.egg-info/top_level.txt