Metadata-Version: 1.0
Name: ewmh
Version: 0.1.3
Summary: python implementation of Extended Window Manager Hints, based on Xlib
Home-page: https://github.com/parkouss/pyewmh
Author: parkouss
Author-email: j.parkouss@gmail.com
License: LGPL
Platform: UNKNOWN
